ciabatta/__init__.py
ciabatta/crandom.py
ciabatta/ejm_rcparams.py
ciabatta/fileio.py
ciabatta/meta.py
ciabatta/network.py
ciabatta/parallel.py
ciabatta/report.py
ciabatta/stats.py
ciabatta-0.7.0.dist-info/DESCRIPTION.rst
ciabatta-0.7.0.dist-info/METADATA
ciabatta-0.7.0.dist-info/RECORD
ciabatta-0.7.0.dist-info/WHEEL
ciabatta-0.7.0.dist-info/metadata.json
ciabatta-0.7.0.dist-info/top_level.txt
